git_helper_utils/__init__.py
git_helper_utils/create_git_branch.py
git_helper_utils/create_git_commit_file.py
git_helper_utils/make_shell_scripts_and_aliases.py
git_helper_utils-0.4.0.dist-info/AUTHORS.rst
git_helper_utils-0.4.0.dist-info/LICENSE
git_helper_utils-0.4.0.dist-info/METADATA
git_helper_utils-0.4.0.dist-info/WHEEL
git_helper_utils-0.4.0.dist-info/entry_points.txt
git_helper_utils-0.4.0.dist-info/top_level.txt
git_helper_utils-0.4.0.dist-info/RECORD
