Metadata-Version: 2.1
Name: git-helper-utils
Version: 0.4.0
Summary: Collection of Python utility scripts to facilitate git related tasks.
Home-page: https://github.com/jai-python3/git-helper-utils
Author: Jaideep Sundaram
Author-email: jai.python3@gmail.com
Keywords: git-helper-utils
Classifier: Development Status :: 2 - Pre-Alpha
Classifier: Intended Audience :: Developers
Classifier: Natural Language :: English
Classifier: Programming Language :: Python :: 3
Classifier: Programming Language :: Python :: 3.6
Classifier: Programming Language :: Python :: 3.7
Classifier: Programming Language :: Python :: 3.8
Requires-Python: >=3.6
License-File: LICENSE
License-File: AUTHORS.rst
Requires-Dist: Click >=7.0
Requires-Dist: Rich
